prfect/__init__.py
prfect/clf.0.24.2.pkl
prfect/clf.1.1.1.pkl
prfect/codons.py
prfect/feature.py
prfect/file.py
prfect/functions.py
prfect/locus.py
prfect/prodigal.py
prfect/stats.py
prfect-0.42.data/scripts/prfect.py
prfect-0.42.dist-info/licenses/LICENSE
prfect-0.42.dist-info/METADATA
prfect-0.42.dist-info/WHEEL
prfect-0.42.dist-info/top_level.txt
prfect-0.42.dist-info/RECORD
