Metadata-Version: 2.4
Name: prfect
Version: 0.42
Summary: A tool to predict programmed ribosomal frameshifts
Home-page: https://github.com/deprekate/prfect
Author: Katelyn McNair
Author-email: deprekate@gmail.com
Classifier: Programming Language :: Python :: 3
Classifier: License :: OSI Approved :: GNU General Public License v3 or later (GPLv3+)
Classifier: Operating System :: OS Independent
Requires-Python: >3.5.2
License-File: LICENSE
Requires-Dist: scikit-learn>=0.24.0
Requires-Dist: numpy
Requires-Dist: pandas
Requires-Dist: genbank
Requires-Dist: LinearFold
Requires-Dist: hotknots
Requires-Dist: score_rbs
Requires-Dist: packaging
Dynamic: author
Dynamic: author-email
Dynamic: classifier
Dynamic: description
Dynamic: description-content-type
Dynamic: home-page
Dynamic: license-file
Dynamic: requires-dist
Dynamic: requires-python
Dynamic: summary
